{
	"credit": "Made with Blockbench",
	"parent": "block/block",
	"textures": {
		"0": "tesseract:blocks/pipe",
		"particle": "tesseract:blocks/pipe"
	},
	"elements": [
		{
			"from": [6, 6, 0],
			"to": [10, 10, 16],
			"rotation": {"angle": 0, "axis": "y", "origin": [14, 8, 8]},
			"faces": {
				"north": {"uv": [4, 0, 8, 4], "texture": "#0"},
				"east": {"uv": [0, 0, 4, 16], "rotation": 90, "texture": "#0"},
				"south": {"uv": [4, 0, 8, 4], "texture": "#0"},
				"west": {"uv": [0, 0, 4, 16], "rotation": 90, "texture": "#0"},
				"up": {"uv": [0, 0, 4, 16], "texture": "#0"},
				"down": {"uv": [0, 0, 4, 16], "texture": "#0"}
			}
		}
	]
}